azureml/__init__.py
azureml/datacollector/__init__.py
azureml/datacollector/modeldatacollector.py
azureml/datacollector/tools/modeldatacollector/lib/native/Linux/libazurestorage.so
azureml/datacollector/tools/modeldatacollector/lib/native/Linux/libazurestorage.so.3
azureml/datacollector/tools/modeldatacollector/lib/native/Linux/libazurestorage.so.3.0
azureml/datacollector/tools/modeldatacollector/lib/native/Linux/libboost_atomic.so
azureml/datacollector/tools/modeldatacollector/lib/native/Linux/libboost_atomic.so.1.64.0
azureml/datacollector/tools/modeldatacollector/lib/native/Linux/libboost_chrono.so
azureml/datacollector/tools/modeldatacollector/lib/native/Linux/libboost_chrono.so.1.64.0
azureml/datacollector/tools/modeldatacollector/lib/native/Linux/libboost_container.so
azureml/datacollector/tools/modeldatacollector/lib/native/Linux/libboost_container.so.1.64.0
azureml/datacollector/tools/modeldatacollector/lib/native/Linux/libboost_context.so
azureml/datacollector/tools/modeldatacollector/lib/native/Linux/libboost_context.so.1.64.0
azureml/datacollector/tools/modeldatacollector/lib/native/Linux/libboost_coroutine.so
azureml/datacollector/tools/modeldatacollector/lib/native/Linux/libboost_coroutine.so.1.64.0
azureml/datacollector/tools/modeldatacollector/lib/native/Linux/libboost_date_time.so
azureml/datacollector/tools/modeldatacollector/lib/native/Linux/libboost_date_time.so.1.64.0
azureml/datacollector/tools/modeldatacollector/lib/native/Linux/libboost_filesystem.so
azureml/datacollector/tools/modeldatacollector/lib/native/Linux/libboost_filesystem.so.1.64.0
azureml/datacollector/tools/modeldatacollector/lib/native/Linux/libboost_graph.so
azureml/datacollector/tools/modeldatacollector/lib/native/Linux/libboost_graph.so.1.64.0
azureml/datacollector/tools/modeldatacollector/lib/native/Linux/libboost_iostreams.so
azureml/datacollector/tools/modeldatacollector/lib/native/Linux/libboost_iostreams.so.1.64.0
azureml.datacollector-0.1.0a13.dist-info/DESCRIPTION.rst
azureml.datacollector-0.1.0a13.dist-info/METADATA
azureml.datacollector-0.1.0a13.dist-info/RECORD
azureml.datacollector-0.1.0a13.dist-info/WHEEL
azureml.datacollector-0.1.0a13.dist-info/metadata.json
azureml.datacollector-0.1.0a13.dist-info/top_level.txt
