Metadata-Version: 2.0
Name: azureml.datacollector
Version: 0.1.0a13
Summary: Microsoft Azure Machine Learning Python SDK for collecting model data during operationalization
Home-page: UNKNOWN
Author: Microsoft Corporation
Author-email: alevine@microsoft.com
License: MIT
Keywords: azure machinelearning model operationalization datacollection
Platform: UNKNOWN
Classifier: Development Status :: 3 - Alpha
Classifier: Intended Audience :: Developers
Classifier: Intended Audience :: System Administrators
Classifier: License :: OSI Approved :: MIT License
Classifier: Programming Language :: Python
Classifier: Programming Language :: Python :: 2
Classifier: Programming Language :: Python :: 2.7
Classifier: Programming Language :: Python :: 3
Classifier: Programming Language :: Python :: 3.5
Classifier: Topic :: Software Development :: Libraries :: Application Frameworks
Classifier: Topic :: Software Development :: Libraries :: Python Modules
